xeno_canto/__init__.py
xeno_canto/constants.py
xeno_canto/patterns.py
xeno_canto/types.py
xeno_canto/client/client.py
xeno_canto/client/client_errors.py
xeno_canto/client/client_http.py
xeno_canto/client/client_params.py
xeno_canto/client/client_schemas.py
xeno_canto/client/client_types.py
xeno_canto/query/field_serializers.py
xeno_canto/query/query_fields.py
xeno_canto/query/query_params.py
xeno_canto/query/query_schema.py
xeno_canto/recording/common_fields.py
xeno_canto/recording/field_serializers.py
xeno_canto/recording/field_validators.py
xeno_canto/recording/recording.py
xeno_canto/recording/recording_fields.py
xeno_canto/recording/recording_schema.py
xeno_canto/recording/resource_schemas.py
xeno_canto/tags/numeric_tag.py
xeno_canto/tags/search_tag.py
xeno_canto/tags/tag_types.py
xeno_canto/tags/tags.py
xc_api_py-0.1.23.dist-info/METADATA
xc_api_py-0.1.23.dist-info/WHEEL
xc_api_py-0.1.23.dist-info/top_level.txt
xc_api_py-0.1.23.dist-info/RECORD
