Metadata-Version: 2.4
Name: xc-api-py
Version: 0.1.23
Summary: An intuitive, type-safe Python wrapper for the Xeno-Canto API
Author-email: yuvalrot <yuvalrot@telhai.ac.il>
License: MIT
Project-URL: Bug Reports, https://github.com/yuvalrot479/xc-api-py/issues
Project-URL: Homepage, https://github.com/yuvalrot479/xc-api-py
Project-URL: Source, https://github.com/yuvalrot479/xc-api-py
Requires-Python: >=3.11
Requires-Dist: pydantic>=2.12.5
Requires-Dist: pycountry>=24.6.1
Requires-Dist: yarl>=1.22.0
Requires-Dist: requests>=2.32.5
Requires-Dist: requests-ratelimiter>=0.7.0
Requires-Dist: requests-cache>=1.2.1
